deraser/__init__.py
deraser/base.py
deraser-0.0.1.dist-info/METADATA
deraser-0.0.1.dist-info/WHEEL
deraser-0.0.1.dist-info/top_level.txt
deraser-0.0.1.dist-info/RECORD
